vfx_seqtools/__init__.py
vfx_seqtools/common_options.py
vfx_seqtools/decorators.py
vfx_seqtools/parser.py
vfx_seqtools/seqchk_cli.py
vfx_seqtools/seqcp_cli.py
vfx_seqtools/seqdo_cli.py
vfx_seqtools/seqexp_cli.py
vfx_seqtools/seqgen_cli.py
vfx_seqtools/seqls_cli.py
vfx_seqtools/seqmv_cli.py
vfx_seqtools/seqrm_cli.py
vfx_seqtools/actions/__init__.py
vfx_seqtools/actions/seqchk.py
vfx_seqtools/actions/seqcp.py
vfx_seqtools/actions/seqdo.py
vfx_seqtools/actions/seqexp.py
vfx_seqtools/actions/seqgen.py
vfx_seqtools/actions/seqls.py
vfx_seqtools/actions/seqmv.py
vfx_seqtools/actions/seqrm.py
vfx_seqtools-0.2.1.dist-info/METADATA
vfx_seqtools-0.2.1.dist-info/WHEEL
vfx_seqtools-0.2.1.dist-info/entry_points.txt
vfx_seqtools-0.2.1.dist-info/licenses/LICENSE
vfx_seqtools-0.2.1.dist-info/RECORD
