Metadata-Version: 2.4
Name: vfx_seqtools
Version: 0.2.1
Summary: CLI utilities for working with VFX frame sequences.
Project-URL: Homepage, https://jdmacleod.github.io/vfx-seqtools/
Project-URL: Repository, https://github.com/jdmacleod/vfx-seqtools.git
Project-URL: Issues, https://github.com/jdmacleod/vfx-seqtools
Project-URL: Changelog, https://github.com/jdmacleod/vfx-seqtools/blob/main/CHANGELOG.md
Author-email: Jason MacLeod <jason.d.macleod@gmail.com>
License-Expression: MIT
License-File: LICENSE
Classifier: Development Status :: 4 - Beta
Classifier: Environment :: Console
Classifier: Framework :: Hatch
Classifier: Framework :: Pytest
Classifier: Intended Audience :: End Users/Desktop
Classifier: Programming Language :: Python :: 3
Classifier: Programming Language :: Python :: 3.9
Classifier: Programming Language :: Python :: 3.10
Classifier: Programming Language :: Python :: 3.11
Classifier: Programming Language :: Python :: 3.12
Classifier: Programming Language :: Python :: 3.13
Classifier: Topic :: Artistic Software
Classifier: Topic :: Multimedia :: Graphics
Classifier: Topic :: Utilities
Requires-Python: >=3.9
Requires-Dist: click<=8.1.8
Requires-Dist: fileseq>=2.1.0
Requires-Dist: openexr>=3.3.0
Requires-Dist: pillow>=11.0.0
Requires-Dist: typer>=0.7.0
Provides-Extra: dev
Requires-Dist: bandit>=1.8.0; extra == 'dev'
Requires-Dist: mypy>=1.0.0; extra == 'dev'
Requires-Dist: pre-commit>=3.5.0; extra == 'dev'
Requires-Dist: pylint>=3.0.0; extra == 'dev'
Requires-Dist: pytest-cov>=4.0.0; extra == 'dev'
Requires-Dist: pytest-html>=4.0.0; extra == 'dev'
Requires-Dist: pytest-mock>=3.10.0; extra == 'dev'
Requires-Dist: pytest>=7.0.0; extra == 'dev'
Requires-Dist: ruff>=0.1.0; extra == 'dev'
Requires-Dist: safety>=3.2.9; extra == 'dev'
Provides-Extra: docs
Requires-Dist: genbadge[all]>=1.0.0; extra == 'docs'
Requires-Dist: mkdocs>=1.6.0; extra == 'docs'
